[{"titulo": "simon1", "contenido": "Crear nuevos objetos de noticia para cada categor\u00eda ingresada", "categoria": "1", "enlace": "simon1"}, {"titulo": "simon1", "contenido": "Crear nuevos objetos de noticia para cada categor\u00eda ingresada", "categoria": "2", "enlace": "simon1"}, {"titulo": "simon1", "contenido": "Crear nuevos objetos de noticia para cada categor\u00eda ingresada", "categoria": "3", "enlace": "simon1"}, {"titulo": "yo19", "contenido": "izar el archivo JSOizar el archivo JSOizar el archivo JSOizar el archivo JSO", "categoria": "1", "enlace": "yo19"}, {"titulo": "yo19", "contenido": "izar el archivo JSOizar el archivo JSOizar el archivo JSOizar el archivo JSO", "categoria": "2", "enlace": "yo19"}, {"titulo": "yo19", "contenido": "izar el archivo JSOizar el archivo JSOizar el archivo JSOizar el archivo JSO", "categoria": "3", "enlace": "yo19"}, {"titulo": "cl", "contenido": "SON en elSON en elSON en elSON en elSON en elSON en elSON en elSON en elSON en elSON en elSON en el", "categoria": "1", "enlace": "cl"}, {"titulo": "cl", "contenido": "SON en elSON en elSON en elSON en elSON en elSON en elSON en elSON en elSON en elSON en elSON en el", "categoria": "2", "enlace": "cl"}, {"titulo": "cl", "contenido": "SON en elSON en elSON en elSON en elSON en elSON en elSON en elSON en elSON en elSON en elSON en el", "categoria": "3", "enlace": "cl"}]